Analysis/Encoding.py
Analysis/Encoding_One_Hot.py
Analysis/__init__.py
Encoding_One_Hot-0.1.11.dist-info/METADATA
Encoding_One_Hot-0.1.11.dist-info/WHEEL
Encoding_One_Hot-0.1.11.dist-info/top_level.txt
Encoding_One_Hot-0.1.11.dist-info/RECORD
